AUTHORS.md
CHANGELOG.md
LICENSE
MANIFEST.in
README.md
setup.py
django_livechat.egg-info/PKG-INFO
django_livechat.egg-info/SOURCES.txt
django_livechat.egg-info/dependency_links.txt
django_livechat.egg-info/not-zip-safe
django_livechat.egg-info/requires.txt
django_livechat.egg-info/top_level.txt
livechat/__init__.py
livechat/admin.py
livechat/context_processors.py
livechat/models.py
livechat/urls.py
livechat/views.py
livechat/migrations/0001_initial.py
livechat/migrations/0002_auto__add_field_livechat_chat_starts_at__add_field_livechat_chat_ends_.py
livechat/migrations/0003_auto__add_field_livechat_expert__add_field_livechat_maximum_questions_.py
livechat/migrations/0004_auto__add_field_livechat_is_archived.py
livechat/migrations/__init__.py
livechat/static/livechat_change_question.js
livechat/templates/admin/livechat/livechat/change_form.html
livechat/templates/admin/livechat/livechat/participate.html
livechat/templates/admin/livechat/livechat/participate_responses.html
livechat/templates/livechat/archived_chat.html
livechat/templates/livechat/embed.html
livechat/templates/livechat/index.html
livechat/templates/livechat/show.html
livechat/templates/livechat/inclusion_tags/last_live_chat_banner.html
livechat/templates/livechat/inclusion_tags/live_chat.html
livechat/templates/livechat/inclusion_tags/live_chat_banner.html
livechat/templatetags/__init__.py
livechat/templatetags/livechat_tags.py
livechat/tests/__init__.py
livechat/tests/test_livechat.py