Metadata-Version: 1.1
Name: django-livechat
Version: 1.0.1
Summary: Very Simple Live Chat Django Application
Home-page: http://github.com/praekelt/django-livechat
Author: Praekelt Foundation
Author-email: dev@praekelt.com
License: BSD
Platform: UNKNOWN
Classifier: Programming Language :: Python
Classifier: License :: OSI Approved :: BSD License
Classifier: Development Status :: 4 - Beta
Classifier: Operating System :: OS Independent
Classifier: Framework :: Django
Classifier: Intended Audience :: Developers
Classifier: Topic :: Internet :: WWW/HTTP :: Dynamic Content
